Metadata-Version: 2.1
Name: django-templates-variables
Version: 2020.7.1
Summary: Django templates variables settings
Home-page: https://github.com/andrewp-as-is/django-templates-variables.py
License: Unlicense
Keywords: django templates variables
Platform: UNKNOWN
Classifier: Framework :: Django
Classifier: License :: Public Domain
Classifier: Operating System :: OS Independent
Classifier: Programming Language :: Python :: 3
